invenio_github/__init__.py
invenio_github/api.py
invenio_github/config.py
invenio_github/errors.py
invenio_github/ext.py
invenio_github/models.py
invenio_github/proxies.py
invenio_github/receivers.py
invenio_github/tasks.py
invenio_github/utils.py
invenio_github/webpack.py
invenio_github/alembic/2f62e6442a08_change_datetime_types.py
invenio_github/alembic/5a5428312b2b_create_github_branch.py
invenio_github/alembic/b0eaee37b545_create_github_tables.py
invenio_github/assets/semantic-ui/js/invenio_github/index.js
invenio_github/oauth/handlers.py
invenio_github/oauth/remote_app.py
invenio_github/templates/semantic-ui/invenio_github/base.html
invenio_github/templates/semantic-ui/invenio_github/helpers.html
invenio_github/templates/semantic-ui/invenio_github/settings/base.html
invenio_github/templates/semantic-ui/invenio_github/settings/helpers.html
invenio_github/templates/semantic-ui/invenio_github/settings/index.html
invenio_github/templates/semantic-ui/invenio_github/settings/index_item.html
invenio_github/templates/semantic-ui/invenio_github/settings/view.html
invenio_github/translations/messages.pot
invenio_github/translations/cs/LC_MESSAGES/messages.mo
invenio_github/translations/cs/LC_MESSAGES/messages.po
invenio_github/translations/da/LC_MESSAGES/messages.mo
invenio_github/translations/da/LC_MESSAGES/messages.po
invenio_github/translations/de/LC_MESSAGES/messages.mo
invenio_github/translations/de/LC_MESSAGES/messages.po
invenio_github/translations/en/LC_MESSAGES/messages.mo
invenio_github/translations/en/LC_MESSAGES/messages.po
invenio_github/translations/es/LC_MESSAGES/messages.mo
invenio_github/translations/es/LC_MESSAGES/messages.po
invenio_github/translations/fr/LC_MESSAGES/messages.mo
invenio_github/translations/fr/LC_MESSAGES/messages.po
invenio_github/translations/it/LC_MESSAGES/messages.mo
invenio_github/translations/it/LC_MESSAGES/messages.po
invenio_github/views/__init__.py
invenio_github/views/badge.py
invenio_github/views/github.py
invenio_github-5.0.0.dist-info/licenses/AUTHORS.rst
invenio_github-5.0.0.dist-info/licenses/LICENSE
invenio_github-5.0.0.dist-info/METADATA
invenio_github-5.0.0.dist-info/WHEEL
invenio_github-5.0.0.dist-info/entry_points.txt
invenio_github-5.0.0.dist-info/top_level.txt
invenio_github-5.0.0.dist-info/RECORD
