Metadata-Version: 2.4
Name: invenio-github
Version: 5.0.0
Summary: "Invenio module that adds GitHub integration to the platform."
Home-page: https://github.com/inveniosoftware/invenio-github
Author: CERN
Author-email: info@inveniosoftware.org
License: MIT
Keywords: invenio github
Platform: any
Classifier: Development Status :: 5 - Production/Stable
Requires-Python: >=3.7
License-File: LICENSE
License-File: AUTHORS.rst
Requires-Dist: Flask-Menu<3.0.0,>=2.0.0
Requires-Dist: PyYAML>=5.4.1
Requires-Dist: email-validator>=1.0.5
Requires-Dist: github3.py<5.0.0,>=4.0.1
Requires-Dist: humanize>=0.5.1
Requires-Dist: invenio-assets<5.0.0,>=4.0.0
Requires-Dist: invenio-accounts<8.0.0,>=7.0.0
Requires-Dist: invenio-celery<3.0.0,>=2.0.0
Requires-Dist: invenio-db<3.0.0,>=2.2.0
Requires-Dist: invenio-formatter<5.0.0,>=4.0.0
Requires-Dist: invenio-i18n<4.0.0,>=3.0.0
Requires-Dist: invenio-oauth2server<5.0.0,>=4.0.0
Requires-Dist: invenio-oauthclient<8.0.0,>=7.0.0
Requires-Dist: invenio-pidstore<4.0.0,>=3.0.0
Requires-Dist: invenio-records-rest<5.0.0,>=4.0.0
Requires-Dist: invenio-webhooks<3.0.0,>=2.0.0
Requires-Dist: invenio-records-resources<10.0.0,>=9.0.0
Requires-Dist: mistune>=0.7.2
Requires-Dist: six>=1.12.0
Requires-Dist: uritemplate>=3.0.1
Provides-Extra: tests
Requires-Dist: httpretty>=0.8.14; extra == "tests"
Requires-Dist: invenio-app<4.0.0,>=3.0.0; extra == "tests"
Requires-Dist: invenio-db[mysql,postgresql]<3.0.0,>=2.2.0; extra == "tests"
Requires-Dist: invenio-files-rest<5.0.0,>=4.0.0; extra == "tests"
Requires-Dist: isort>=4.2.2; extra == "tests"
Requires-Dist: mock>=2.0.0; extra == "tests"
Requires-Dist: pytest-black>=0.6.0; extra == "tests"
Requires-Dist: pytest-invenio<5.0.0,>=4.0.0; extra == "tests"
Requires-Dist: pytest-mock>=2.0.0; extra == "tests"
Requires-Dist: sphinx>=4.5.0; extra == "tests"
Provides-Extra: elasticsearch7
Requires-Dist: invenio-search[elasticsearch7]<4.0.0,>=3.0.0; extra == "elasticsearch7"
Provides-Extra: opensearch1
Requires-Dist: invenio-search[opensearch1]<4.0.0,>=3.0.0; extra == "opensearch1"
Provides-Extra: opensearch2
Requires-Dist: invenio-search[opensearch2]<4.0.0,>=3.0.0; extra == "opensearch2"
Dynamic: license-file
